staker/__init__.py
staker/config.py
staker/environment.py
staker/mev.py
staker/node.py
staker/snapshot.py
staker/utils.py
staker-0.2.1.dist-info/METADATA
staker-0.2.1.dist-info/WHEEL
staker-0.2.1.dist-info/entry_points.txt
staker-0.2.1.dist-info/licenses/LICENSE
staker-0.2.1.dist-info/RECORD
