Metadata-Version: 2.4
Name: staker
Version: 0.2.1
Summary: Ethereum staking node orchestrator
Project-URL: Homepage, https://github.com/alkalescent/ethereum
Project-URL: Repository, https://github.com/alkalescent/ethereum
Author: Krish Suchak
License-Expression: MIT
License-File: LICENSE
Classifier: Development Status :: 4 - Beta
Classifier: License :: OSI Approved :: MIT License
Classifier: Programming Language :: Python :: 3.11
Classifier: Programming Language :: Python :: 3.12
Classifier: Programming Language :: Python :: 3.13
Classifier: Topic :: System :: Networking
Requires-Python: >=3.11
Requires-Dist: boto3
Requires-Dist: requests
Requires-Dist: rich
